glue_jupyterlab/__init__.py
glue_jupyterlab/_version.py
glue_jupyterlab/glue_session.py
glue_jupyterlab/glue_utils.py
glue_jupyterlab/glue_ydoc.py
glue_jupyterlab/handlers.py
glue_jupyterlab/tests/__init__.py
glue_jupyterlab/tests/conftest.py
glue_jupyterlab/tests/test_glue_session.py
glue_jupyterlab/tests/test_handlers.py
glue_jupyterlab/tests/test_ydoc.py
glue_jupyterlab-0.3.0.data/data/etc/jupyter/jupyter_notebook_config.d/glue_jupyterlab.json
glue_jupyterlab-0.3.0.data/data/etc/jupyter/jupyter_server_config.d/glue_jupyterlab.json
glue_jupyterlab-0.3.0.data/data/share/jupyter/labextensions/glue-jupyterlab/package.json
glue_jupyterlab-0.3.0.data/data/share/jupyter/labextensions/glue-jupyterlab/static/185.0cff412fc25ed146b7c1.js
glue_jupyterlab-0.3.0.data/data/share/jupyter/labextensions/glue-jupyterlab/static/722.e912ef3d95501737406e.js
glue_jupyterlab-0.3.0.data/data/share/jupyter/labextensions/glue-jupyterlab/static/797.6775a9c675159fcc67ec.js
glue_jupyterlab-0.3.0.data/data/share/jupyter/labextensions/glue-jupyterlab/static/929.a029633e30c80e22d788.js
glue_jupyterlab-0.3.0.data/data/share/jupyter/labextensions/glue-jupyterlab/static/929.a029633e30c80e22d788.js.LICENSE.txt
glue_jupyterlab-0.3.0.data/data/share/jupyter/labextensions/glue-jupyterlab/static/remoteEntry.5c208e7340414ff77977.js
glue_jupyterlab-0.3.0.data/data/share/jupyter/labextensions/glue-jupyterlab/static/style.js
glue_jupyterlab-0.3.0.data/data/share/jupyter/labextensions/glue-jupyterlab/static/third-party-licenses.json
glue_jupyterlab-0.3.0.data/data/share/jupyter/labextensions/glue-jupyterlab/install.json
glue_jupyterlab-0.3.0.dist-info/METADATA
glue_jupyterlab-0.3.0.dist-info/WHEEL
glue_jupyterlab-0.3.0.dist-info/entry_points.txt
glue_jupyterlab-0.3.0.dist-info/licenses/LICENSE
glue_jupyterlab-0.3.0.dist-info/RECORD
