Metadata-Version: 2.1
Name: glue-jupyterlab
Version: 0.3.0
Summary: A JupyterLab extension for glue-viz
Project-URL: Homepage, https://github.com/QuantStack/glue-jupyterlab
Project-URL: Bug Tracker, https://github.com/QuantStack/glue-jupyterlab/issues
Project-URL: Repository, https://github.com/QuantStack/glue-jupyterlab.git
Author-email: QuantStack <info@quantstack.net>
License: BSD 3-Clause License
License-File: LICENSE
Classifier: Framework :: Jupyter
Classifier: Framework :: Jupyter :: JupyterLab
Classifier: Framework :: Jupyter :: JupyterLab :: 3
Classifier: Framework :: Jupyter :: JupyterLab :: Extensions
Classifier: Framework :: Jupyter :: JupyterLab :: Extensions :: Prebuilt
Classifier: License :: OSI Approved :: BSD License
Classifier: Programming Language :: Python
Classifier: Programming Language :: Python :: 3
Classifier: Programming Language :: Python :: 3.7
Classifier: Programming Language :: Python :: 3.8
Classifier: Programming Language :: Python :: 3.9
Classifier: Programming Language :: Python :: 3.10
Classifier: Programming Language :: Python :: 3.11
Requires-Python: >=3.7
Requires-Dist: glue-core
Requires-Dist: glue-jupyter
Requires-Dist: jupyter-collaboration<2.0.0,>=1.0.0
Requires-Dist: jupyter-server<3,>=1.21
Requires-Dist: yjs-widgets<0.4.0,>=0.3.3
Requires-Dist: ypywidgets<0.5.0,>=0.4.0
Provides-Extra: test
Requires-Dist: coverage; extra == 'test'
Requires-Dist: pytest; extra == 'test'
Requires-Dist: pytest-asyncio; extra == 'test'
Requires-Dist: pytest-cov; extra == 'test'
Requires-Dist: pytest-jupyter[server]>=0.6.0; extra == 'test'
